zparser2/__init__.py
zparser2/common.py
zparser2/web.py
zparser2-0.0.14.dist-info/licenses/LICENSE
zparser2-0.0.14.dist-info/METADATA
zparser2-0.0.14.dist-info/WHEEL
zparser2-0.0.14.dist-info/top_level.txt
zparser2-0.0.14.dist-info/RECORD
