Metadata-Version: 2.4
Name: zparser2
Version: 0.0.14
Summary: ZParser Cli Argument Library. Nothing comes after Z
Author: Marcos Diez, Benjamin Port
License-Expression: BSD-3-Clause
Project-URL: Homepage, https://github.com/marcosdiez/zparser2
Project-URL: Issues, https://github.com/marcosdiez/zparser2/issues
Keywords: cli,argument,parsing
Classifier: Development Status :: 5 - Production/Stable
Classifier: Intended Audience :: Developers
Classifier: Operating System :: OS Independent
Classifier: Programming Language :: Python :: 3
Classifier: Environment :: Console
Classifier: Topic :: Software Development :: Libraries
Requires-Python: >=3.6
License-File: LICENSE
Dynamic: license-file
